abstractor-4.1.1.data/scripts/abstractor
libabstractor/QueryLibrary.py
libabstractor/RdfGraph.py
libabstractor/SparqlQuery.py
libabstractor/__init__.py
abstractor-4.1.1.dist-info/LICENSE
abstractor-4.1.1.dist-info/METADATA
abstractor-4.1.1.dist-info/WHEEL
abstractor-4.1.1.dist-info/top_level.txt
abstractor-4.1.1.dist-info/RECORD
